{"IcoMoonType":"selection","icons":[{"icon":{"paths":["M910.221 0h-797.012c-62.862 0-112.64 50.916-112.64 113.778l-0.569 796.443c0 62.861 50.347 113.779 113.209 113.779h797.012c62.861 0 113.779-50.918 113.779-113.779v-796.443c0-62.862-50.918-113.778-113.779-113.778zM910.221 682.669h-227.552c0 94.15-76.518 170.662-170.669 170.662s-170.667-76.512-170.667-170.662h-228.124v-568.891h797.012v568.891zM625.778 398.222h113.78l-227.558 227.556-227.556-227.556h113.778v-170.666h227.556v170.666z"],"attrs":[],"isMulticolor":false,"isMulticolor2":false,"grid":0,"tags":["archive"],"colorPermutations":{}},"attrs":[],"properties":{"order":7,"id":11,"name":"archive","prevSize":32,"code":59648},"setIdx":0,"setId":0,"iconIdx":0},{"icon":{"paths":["M750.911 932.978h-477.866c-37.703 0-68.267-30.566-68.267-68.267v-614.401h614.399v614.401c0 37.7-30.561 68.267-68.267 68.267z","M409.589 728.178v-273.067","M614.423 728.178v-273.067","M68.278 250.311h887.467","M614.4 113.778h-204.8c-37.703 0-68.267 30.564-68.267 68.267v68.267h341.333v-68.267c0-37.703-30.566-68.267-68.267-68.267z"],"attrs":[{"fill":"none","strokeLinejoin":"round","strokeLinecap":"round","strokeMiterlimit":"4","strokeWidth":68.26666666666667},{"fill":"none","strokeLinejoin":"round","strokeLinecap":"round","strokeMiterlimit":"4","strokeWidth":68.26666666666667},{"fill":"none","strokeLinejoin":"round","strokeLinecap":"round","strokeMiterlimit":"4","strokeWidth":68.26666666666667},{"fill":"none","strokeLinejoin":"round","strokeLinecap":"round","strokeMiterlimit":"4","strokeWidth":68.26666666666667},{"fill":"none","strokeLinejoin":"round","strokeLinecap":"round","strokeMiterlimit":"4","strokeWidth":68.26666666666667}],"isMulticolor":false,"isMulticolor2":false,"grid":0,"tags":["bin"],"colorPermutations":{}},"attrs":[{"fill":"none","strokeLinejoin":"round","strokeLinecap":"round","strokeMiterlimit":"4","strokeWidth":68.26666666666667},{"fill":"none","strokeLinejoin":"round","strokeLinecap":"round","strokeMiterlimit":"4","strokeWidth":68.26666666666667},{"fill":"none","strokeLinejoin":"round","strokeLinecap":"round","strokeMiterlimit":"4","strokeWidth":68.26666666666667},{"fill":"none","strokeLinejoin":"round","strokeLinecap":"round","strokeMiterlimit":"4","strokeWidth":68.26666666666667},{"fill":"none","strokeLinejoin":"round","strokeLinecap":"round","strokeMiterlimit":"4","strokeWidth":68.26666666666667}],"properties":{"order":8,"id":10,"name":"bin","prevSize":32,"code":59649},"setIdx":0,"setId":0,"iconIdx":1},{"icon":{"paths":["M693.333 56.889h199.108v113.778h-796.442v-113.778h199.111l56.889-56.889h284.444l56.889 56.889zM266.667 1024c-62.578 0-113.778-51.2-113.778-113.779v-682.665h682.67v682.665c0 62.579-51.2 113.779-113.78 113.779h-455.111z"],"attrs":[],"isMulticolor":false,"isMulticolor2":false,"grid":0,"tags":["delete"],"colorPermutations":{}},"attrs":[],"properties":{"order":9,"id":9,"name":"delete","prevSize":32,"code":59650},"setIdx":0,"setId":0,"iconIdx":2},{"icon":{"paths":["M898.463 125.534c-26.095-25.983-61.491-40.461-98.315-40.211s-72.021 15.205-97.758 41.539l-549.928 549.928-67.129 261.877 261.878-67.169 549.926-549.924c26.34-25.729 41.301-60.922 41.552-97.743s-14.234-72.213-40.226-98.297z","M686.666 142.602l194.714 194.711","M152.5 676.75l194.901 194.56"],"attrs":[{"fill":"none","strokeLinejoin":"round","strokeLinecap":"round","strokeMiterlimit":"4","strokeWidth":68.26666666666667},{"fill":"none","strokeLinejoin":"round","strokeLinecap":"round","strokeMiterlimit":"4","strokeWidth":68.26666666666667},{"fill":"none","strokeLinejoin":"round","strokeLinecap":"round","strokeMiterlimit":"4","strokeWidth":68.26666666666667}],"isMulticolor":false,"isMulticolor2":false,"grid":0,"tags":["draft-pencil"],"colorPermutations":{}},"attrs":[{"fill":"none","strokeLinejoin":"round","strokeLinecap":"round","strokeMiterlimit":"4","strokeWidth":68.26666666666667},{"fill":"none","strokeLinejoin":"round","strokeLinecap":"round","strokeMiterlimit":"4","strokeWidth":68.26666666666667},{"fill":"none","strokeLinejoin":"round","strokeLinecap":"round","strokeMiterlimit":"4","strokeWidth":68.26666666666667}],"properties":{"order":10,"id":8,"name":"draft-pencil","prevSize":32,"code":59651},"setIdx":0,"setId":0,"iconIdx":3},{"icon":{"paths":["M162.889 201.697h698.18c47.128 0 85.333 38.205 85.333 85.333v449.94c0 47.128-38.205 85.333-85.333 85.333h-698.18c-47.128 0-85.333-38.205-85.333-85.333v-449.94c0-47.128 38.205-85.333 85.333-85.333z","M932.409 224.452l-336.947 259.165c-49.199 37.846-117.705 37.846-166.903 0l-336.948-259.165"],"attrs":[{"fill":"none","strokeLinejoin":"round","strokeLinecap":"round","strokeMiterlimit":"4","strokeWidth":68.26666666666667},{"fill":"none","strokeLinejoin":"round","strokeLinecap":"round","strokeMiterlimit":"4","strokeWidth":68.26666666666667}],"isMulticolor":false,"isMulticolor2":false,"grid":0,"tags":["email-action-unread"],"colorPermutations":{}},"attrs":[{"fill":"none","strokeLinejoin":"round","strokeLinecap":"round","strokeMiterlimit":"4","strokeWidth":68.26666666666667},{"fill":"none","strokeLinejoin":"round","strokeLinecap":"round","strokeMiterlimit":"4","strokeWidth":68.26666666666667}],"properties":{"order":11,"id":7,"name":"email-action-unread","prevSize":32,"code":59652},"setIdx":0,"setId":0,"iconIdx":4},{"icon":{"paths":["M711.111 739.556c31.42 0 56.889-25.469 56.889-56.889s-25.469-56.889-56.889-56.889c-31.42 0-56.889 25.469-56.889 56.889s25.469 56.889 56.889 56.889z","M759.427 462.696l16.765 55.107c5.74 18.979 25.202 30.267 44.527 25.828l55.825-12.933c21.732-4.931 44.134 4.891 55.233 24.212 11.093 19.321 8.289 43.624-6.918 59.906l-39.060 42.138c-13.54 14.558-13.54 37.097 0 51.655l39.060 42.138c15.206 16.282 18.011 40.585 6.918 59.904-11.099 19.325-33.502 29.144-55.233 24.212l-55.825-12.931c-19.325-4.437-38.787 6.849-44.527 25.828l-16.765 54.881c-6.394 21.339-26.038 35.959-48.316 35.959s-41.921-14.62-48.316-35.959l-16.805-55.108c-5.723-18.972-25.168-30.265-44.487-25.828l-55.863 12.931c-21.729 4.932-44.133-4.887-55.231-24.212-11.098-19.319-8.293-43.622 6.914-59.904l39.063-42.138c13.538-14.558 13.538-37.097 0-51.655l-39.063-42.138c-15.207-16.282-18.012-40.585-6.914-59.906s33.502-29.142 55.231-24.212l55.863 12.933c19.319 4.437 38.764-6.855 44.487-25.828l16.805-55.107c6.446-21.327 26.123-35.897 48.401-35.845s41.887 14.716 48.23 36.073z","M934.343 424.77c-23.427-160.313-141.642-290.454-298.974-329.13s-322.412 21.821-417.495 153.002c-95.084 131.181-101.213 306.891-15.502 444.378l-117.039 245.646 245.532-116.964c12.928 8.044 26.299 15.349 40.050 21.885"],"attrs":[{"fill":"none","strokeLinejoin":"round","strokeLinecap":"round","strokeMiterlimit":"4","strokeWidth":68.26666666666667},{"fill":"none","strokeLinejoin":"round","strokeLinecap":"round","strokeMiterlimit":"4","strokeWidth":68.26666666666667},{"fill":"none","strokeLinejoin":"round","strokeLinecap":"round","strokeMiterlimit":"4","strokeWidth":68.26666666666667}],"isMulticolor":false,"isMulticolor2":false,"grid":0,"tags":["important"],"colorPermutations":{}},"attrs":[{"fill":"none","strokeLinejoin":"round","strokeLinecap":"round","strokeMiterlimit":"4","strokeWidth":68.26666666666667},{"fill":"none","strokeLinejoin":"round","strokeLinecap":"round","strokeMiterlimit":"4","strokeWidth":68.26666666666667},{"fill":"none","strokeLinejoin":"round","strokeLinecap":"round","strokeMiterlimit":"4","strokeWidth":68.26666666666667}],"properties":{"order":12,"id":6,"name":"important","prevSize":32,"code":59653},"setIdx":0,"setId":0,"iconIdx":5},{"icon":{"paths":["M512 0c-282.624 0-512 229.376-512 512s229.376 512 512 512c282.624 0 512-229.376 512-512s-229.376-512-512-512zM460.8 768v-307.2h102.4v307.2h-102.4zM460.8 256v102.4h102.4v-102.4h-102.4z"],"attrs":[],"isMulticolor":false,"isMulticolor2":false,"grid":0,"tags":["information"],"colorPermutations":{}},"attrs":[],"properties":{"order":13,"id":5,"name":"information","prevSize":32,"code":59654},"setIdx":0,"setId":0,"iconIdx":6},{"icon":{"paths":["M583.915 755.061c164.43-69.885 241.080-259.833 171.201-424.265-69.885-164.433-259.834-241.081-424.267-171.199s-241.081 259.832-171.198 424.264c69.882 164.435 259.832 241.079 424.264 171.2z","M686.116 686.056l250.904 250.94"],"attrs":[{"fill":"none","opacity":0.5,"strokeLinejoin":"round","strokeLinecap":"round","strokeMiterlimit":"4","strokeWidth":90.35294117647058},{"fill":"none","opacity":0.5,"strokeLinejoin":"round","strokeLinecap":"round","strokeMiterlimit":"4","strokeWidth":90.35294117647058}],"isMulticolor":false,"isMulticolor2":false,"grid":0,"tags":["search"],"colorPermutations":{}},"attrs":[{"fill":"none","opacity":0.5,"strokeLinejoin":"round","strokeLinecap":"round","strokeMiterlimit":"4","strokeWidth":90.35294117647058},{"fill":"none","opacity":0.5,"strokeLinejoin":"round","strokeLinecap":"round","strokeMiterlimit":"4","strokeWidth":90.35294117647058}],"properties":{"order":14,"id":4,"name":"search","prevSize":32,"code":59655},"setIdx":0,"setId":0,"iconIdx":7},{"icon":{"paths":["M87.469 443.178c-26.79-7.557-45.525-31.694-46.201-59.521s16.865-52.845 43.257-61.695l856.364-279.296c11.437-3.728 24-0.737 32.525 7.747 8.531 8.484 11.59 21.030 7.923 32.487l-279.085 856.792c-8.806 26.438-33.85 44.026-61.709 43.334-27.863-0.685-52.009-19.482-59.507-46.323l-95.829-398.123-397.739-95.403z","M973.421 50.347l-488.234 488.234"],"attrs":[{"fill":"none","strokeLinejoin":"round","strokeLinecap":"round","strokeMiterlimit":"4","strokeWidth":76.8},{"fill":"none","strokeLinejoin":"round","strokeLinecap":"round","strokeMiterlimit":"4","strokeWidth":76.8}],"isMulticolor":false,"isMulticolor2":false,"grid":0,"tags":["send-email"],"colorPermutations":{}},"attrs":[{"fill":"none","strokeLinejoin":"round","strokeLinecap":"round","strokeMiterlimit":"4","strokeWidth":76.8},{"fill":"none","strokeLinejoin":"round","strokeLinecap":"round","strokeMiterlimit":"4","strokeWidth":76.8}],"properties":{"order":15,"id":3,"name":"send-email","prevSize":32,"code":59656},"setIdx":0,"setId":0,"iconIdx":8},{"icon":{"paths":["M512.020 783.047c-8.317 0-15.059 6.746-15.059 15.059 0 8.318 6.742 15.059 15.059 15.059s15.059-6.74 15.059-15.059c0-8.312-6.742-15.059-15.059-15.059v0","M512.020 662.576v-301.173","M577.094 100.784c-12.192-24.821-37.44-40.549-65.094-40.549s-52.902 15.727-65.094 40.549l-380.406 774.947c-9.31 18.938-8.184 41.339 2.977 59.247 11.16 17.914 30.775 28.792 51.877 28.774h781.29c21.106 0.018 40.719-10.86 51.881-28.774 11.162-17.908 12.288-40.309 2.976-59.247l-380.406-774.947z"],"attrs":[{"fill":"none","strokeLinejoin":"round","strokeLinecap":"round","strokeMiterlimit":"4","strokeWidth":72.28235294117647},{"fill":"none","strokeLinejoin":"miter","strokeLinecap":"round","strokeMiterlimit":"4","strokeWidth":72.28235294117647},{"fill":"none","strokeLinejoin":"round","strokeLinecap":"round","strokeMiterlimit":"4","strokeWidth":72.28235294117647}],"isMulticolor":false,"isMulticolor2":false,"grid":0,"tags":["spam-icon"],"colorPermutations":{}},"attrs":[{"fill":"none","strokeLinejoin":"round","strokeLinecap":"round","strokeMiterlimit":"4","strokeWidth":72.28235294117647},{"fill":"none","strokeLinejoin":"miter","strokeLinecap":"round","strokeMiterlimit":"4","strokeWidth":72.28235294117647},{"fill":"none","strokeLinejoin":"round","strokeLinecap":"round","strokeMiterlimit":"4","strokeWidth":72.28235294117647}],"properties":{"order":16,"id":2,"name":"spam-icon","prevSize":32,"code":59657},"setIdx":0,"setId":0,"iconIdx":9},{"icon":{"paths":["M539.641 102.4l126.897 251.411 244.247 24.197c11.873 0.986 22.084 8.789 26.163 19.985 4.073 11.196 1.263 23.739-7.202 32.125l-201.006 199.227 74.524 270.711c3.112 11.73-0.939 24.195-10.359 31.846s-22.454 9.068-33.297 3.618l-247.616-122.618-247.277 122.465c-10.842 5.45-23.874 4.039-33.293-3.612s-13.475-20.122-10.36-31.846l74.524-270.717-201.159-199.225c-8.462-8.387-11.273-20.929-7.198-32.125s14.288-18.999 26.161-19.985l244.243-24.197 126.71-251.259c5.313-10.377 15.99-16.905 27.648-16.905s22.335 6.528 27.648 16.905z"],"attrs":[{"fill":"none","strokeLinejoin":"round","strokeLinecap":"round","strokeMiterlimit":"4","strokeWidth":68.26666666666667}],"isMulticolor":false,"isMulticolor2":false,"grid":0,"tags":["star"],"colorPermutations":{}},"attrs":[{"fill":"none","strokeLinejoin":"round","strokeLinecap":"round","strokeMiterlimit":"4","strokeWidth":68.26666666666667}],"properties":{"order":17,"id":1,"name":"star","prevSize":32,"code":59658},"setIdx":0,"setId":0,"iconIdx":10},{"icon":{"paths":["M541.422 74.921l135.362 268.171 260.523 25.809c12.663 1.052 23.558 9.376 27.904 21.317s1.348 25.321-7.68 34.266l-214.403 212.506 79.491 288.762c3.322 12.51-1.001 25.805-11.048 33.968-10.052 8.164-23.95 9.671-35.516 3.857l-264.124-130.788-263.761 130.623c-11.565 5.82-25.465 4.306-35.512-3.851-10.047-8.164-14.372-21.458-11.050-33.974l79.492-288.757-214.568-212.508c-9.026-8.946-12.024-22.324-7.678-34.266s15.241-20.265 27.905-21.317l260.525-25.81 135.157-268.009c5.667-11.069 17.055-18.032 29.491-18.032s23.824 6.963 29.491 18.032z"],"attrs":[{"strokeLinejoin":"round","strokeLinecap":"round","strokeMiterlimit":"4","strokeWidth":68.26666666666667}],"isMulticolor":false,"isMulticolor2":false,"grid":0,"tags":["star-clicked"],"colorPermutations":{}},"attrs":[{"strokeLinejoin":"round","strokeLinecap":"round","strokeMiterlimit":"4","strokeWidth":68.26666666666667}],"properties":{"order":18,"id":0,"name":"star-clicked","prevSize":32,"code":59659},"setIdx":0,"setId":0,"iconIdx":11}],"height":1024,"metadata":{"name":"dash-stack-icons"},"preferences":{"showGlyphs":true,"showQuickUse":true,"showQuickUse2":true,"showSVGs":true,"fontPref":{"prefix":"icon-","metadata":{"fontFamily":"dash-stack-icons","majorVersion":1,"minorVersion":0},"metrics":{"emSize":1024,"baseline":6.25,"whitespace":50},"embed":false},"imagePref":{"prefix":"icon-","png":true,"useClassSelector":true,"color":0,"bgColor":16777215,"classSelector":".icon"},"historySize":50,"showCodes":true,"gridSize":16}}